topolib/__init__.py
topolib/analysis/__init__.py
topolib/analysis/metrics.py
topolib/analysis/traffic_matrix.py
topolib/assets/Australia-8nodes.json
topolib/assets/Austria-15nodes.json
topolib/assets/Austria-21nodes.json
topolib/assets/Austria-22nodes.json
topolib/assets/Belarus-12nodes.json
topolib/assets/Brazil-28nodes.json
topolib/assets/Bulgaria-38nodes.json
topolib/assets/China-36nodes.json
topolib/assets/China-36nodes_2.json
topolib/assets/China-36nodes_3.json
topolib/assets/Croatia-36nodes.json
topolib/assets/Czech-23nodes.json
topolib/assets/Estonia-10nodes.json
topolib/assets/Europe-16nodes.json
topolib/assets/Europe-20nodes.json
topolib/assets/Europe-26nodes.json
topolib/assets/Europe-27nodes.json
topolib/assets/Europe-42nodes.json
topolib/assets/Europe-9nodes.json
topolib/assets/Finland-13nodes.json
topolib/assets/France-43nodes.json
topolib/assets/France-45nodes.json
topolib/assets/Germany-14nodes.json
topolib/assets/Germany-17nodes.json
topolib/assets/Germany-50nodes.json
topolib/assets/Greece-75nodes.json
topolib/assets/Hungary-52nodes.json
topolib/assets/India-18nodes.json
topolib/assets/India-31nodes.json
topolib/assets/Ireland-17nodes.json
topolib/assets/Italia-21nodes.json
topolib/assets/Japan-12nodes.json
topolib/assets/Japan-35nodes.json
topolib/assets/Korea-10nodes.json
topolib/assets/Lithuania-10nodes.json
topolib/assets/North-America-17nodes.json
topolib/assets/North-America-39nodes.json
topolib/assets/Poland-12nodes.json
topolib/assets/Poland-19nodes.json
topolib/assets/Poland-21nodes.json
topolib/assets/Portugal-12nodes.json
topolib/assets/Romania-16nodes.json
topolib/assets/Romania-21nodes.json
topolib/assets/SAU-28nodes.json
topolib/assets/Serbia-55nodes.json
topolib/assets/Serbia-6nodes.json
topolib/assets/Slovakia-19nodes.json
topolib/assets/Slovakia-50nodes.json
topolib/assets/Slovenia-17nodes.json
topolib/assets/South-Africa-7nodes.json
topolib/assets/Spain-21nodes.json
topolib/assets/Spain-30nodes.json
topolib-0.16.0.dist-info/METADATA
topolib-0.16.0.dist-info/WHEEL
topolib-0.16.0.dist-info/licenses/LICENSE
topolib-0.16.0.dist-info/RECORD
