Metadata-Version: 2.4
Name: topolib
Version: 0.16.0
Summary: A compact Python library for modeling, analyzing, and visualizing optical network topologies.
License: MIT
License-File: LICENSE
Keywords: network,topology,optical,analysis,visualization
Author: Danilo Bórquez-Paredes
Author-email: danilo.borquez.p@uai.cl
Requires-Python: >=3.10
Classifier: Development Status :: 4 - Beta
Classifier: Intended Audience :: Developers
Classifier: Intended Audience :: Science/Research
Classifier: Intended Audience :: Telecommunications Industry
Classifier: License :: OSI Approved :: MIT License
Classifier: Operating System :: OS Independent
Classifier: Programming Language :: Python :: 3
Classifier: Programming Language :: Python :: 3.10
Classifier: Programming Language :: Python :: 3.11
Classifier: Programming Language :: Python :: 3.12
Classifier: Programming Language :: Python :: 3.13
Classifier: Programming Language :: Python :: 3.14
Classifier: Topic :: Scientific/Engineering
Classifier: Topic :: Scientific/Engineering :: Information Analysis
Classifier: Topic :: Scientific/Engineering :: Visualization
Classifier: Topic :: Software Development :: Libraries :: Python Modules
Requires-Dist: PyQt6 (>=6.0)
Requires-Dist: PyQt6-WebEngine (>=6.0)
Requires-Dist: folium (>=0.14.0)
Requires-Dist: jsonschema (>=4.0)
Requires-Dist: networkx (>=2.6)
Requires-Dist: numpy (>=1.21)
Requires-Dist: scipy (>=1.7)
Project-URL: Documentation, https://topolib.readthedocs.io/
Project-URL: Homepage, https://gitlab.com/DaniloBorquez/topolib
Project-URL: Repository, https://gitlab.com/DaniloBorquez/topolib
